astrux/__init__.py
astrux/_errors.py
astrux/_types.py
astrux/_version.py
astrux/client.py
astrux-0.1.2.dist-info/METADATA
astrux-0.1.2.dist-info/WHEEL
astrux-0.1.2.dist-info/licenses/LICENSE
astrux-0.1.2.dist-info/RECORD
