Metadata-Version: 2.4
Name: astrux
Version: 0.1.2
Summary: Astrux Python SDK
Project-URL: Homepage, https://astrux.io
Project-URL: Documentation, https://astrux.io/docs
Author-email: Thomas Bodénan <thomas.bodenan@gmail.com>
License: MIT
License-File: LICENSE
Requires-Python: >=3.8
Requires-Dist: httpx>=0.27.0
